singgalang/__init__.py
singgalang/main.py
singgalang/singgalang.py
singgalang-0.6.data/scripts/singgalang
singgalang-0.6.dist-info/METADATA
singgalang-0.6.dist-info/WHEEL
singgalang-0.6.dist-info/top_level.txt
singgalang-0.6.dist-info/RECORD
